bolt/__init__.py
bolt/ast.py
bolt/codegen.py
bolt/commands.py
bolt/contrib/__init__.py
bolt/contrib/debug_codegen.py
bolt/contrib/defer.py
bolt/contrib/sandbox.py
bolt/emit.py
bolt/helpers.py
bolt/loop_info.py
bolt/memo.py
bolt/module.py
bolt/parse.py
bolt/pattern.py
bolt/plugin.py
bolt/py.typed
bolt/resources/__init__.py
bolt/resources/commands.json
bolt/runtime.py
bolt/semantics.py
bolt/utils.py
bolt-0.50.1.dist-info/licenses/LICENSE
bolt-0.50.1.dist-info/WHEEL
bolt-0.50.1.dist-info/entry_points.txt
bolt-0.50.1.dist-info/METADATA
bolt-0.50.1.dist-info/RECORD
