Metadata-Version: 2.4
Name: bolt
Version: 0.50.1
Summary: Supercharge Minecraft commands with Python
Keywords: beet,minecraft,minecraft-commands,scripting-language,mcfunction
Author: Valentin Berlier
Author-email: Valentin Berlier <berlier.v@gmail.com>
License-Expression: MIT
License-File: LICENSE
Requires-Dist: beet>=0.113.0
Requires-Dist: mecha>=0.102.1
Requires-Python: >=3.14
Project-URL: Repository, https://github.com/mcbeet/beet/blob/main/packages/bolt
